{
  "constituency": {
    "id": 69,
    "number": 69,
    "name": "KAIPAMANGALAM",
    "district": "Thrissur"
  },
  "live_result": {
    "status": "IN_PROGRESS",
    "total_electors": 182716,
    "votes_polled": 140819,
    "votes_counted": 52136,
    "valid_votes": 51614,
    "rounds_completed": 4,
    "total_rounds": 13,
    "last_updated": "2026-04-29T11:27:22.883412+00:00"
  },
  "candidates_2026": [
    {
      "name": "Athulya Ghosh",
      "party": "BDJS",
      "alliance": "NDA",
      "votes": 22022,
      "percentage": 44.3,
      "is_winner": false,
      "is_leading": true
    },
    {
      "name": "T. M. Nazar",
      "party": "INC",
      "alliance": "UDF",
      "votes": 19879,
      "percentage": 39.99,
      "is_winner": false,
      "is_leading": false
    },
    {
      "name": "K. K. Valsaraj",
      "party": "CPI",
      "alliance": "LDF",
      "votes": 6650,
      "percentage": 13.38,
      "is_winner": false,
      "is_leading": false
    },
    {
      "name": "Jayan Eratt",
      "party": "AAP",
      "alliance": "OTH",
      "votes": 506,
      "percentage": 1.02,
      "is_winner": false,
      "is_leading": false
    },
    {
      "name": "Manoj M.M.",
      "party": "CPIML Red Star",
      "alliance": "OTH",
      "votes": 441,
      "percentage": 0.89,
      "is_winner": false,
      "is_leading": false
    },
    {
      "name": "A.M. Muhammed Riyas",
      "party": "SDPI",
      "alliance": "OTH",
      "votes": 214,
      "percentage": 0.43,
      "is_winner": false,
      "is_leading": false
    }
  ],
  "results_2021": [
    {
      "candidate": "E T TAISON MASTER",
      "party": "CPI",
      "votes": 73161,
      "percentage": 53.76,
      "is_winner": true
    },
    {
      "candidate": "SOBHA SUBIN",
      "party": "INC",
      "votes": 50463,
      "percentage": 37.08,
      "is_winner": false
    },
    {
      "candidate": "C D SREELAL",
      "party": "BDJS",
      "votes": 9066,
      "percentage": 6.66,
      "is_winner": false
    },
    {
      "candidate": "M K ASLAM",
      "party": "WPOI",
      "votes": 1671,
      "percentage": 1.23,
      "is_winner": false
    },
    {
      "candidate": "M K SHAMEER",
      "party": "SDPI",
      "votes": 814,
      "percentage": 0.6,
      "is_winner": false
    }
  ]
}