{
  "constituency": {
    "id": 84,
    "number": 84,
    "name": "KUNNATHUNAD",
    "district": "Ernakulam"
  },
  "live_result": null,
  "candidates_2026": [
    {
      "name": "V. P. Sajeendran",
      "party": "INC",
      "alliance": "UDF",
      "votes": 0,
      "percentage": 0.0,
      "is_winner": false,
      "is_leading": false
    },
    {
      "name": "Babu Divakaran",
      "party": "TTP",
      "alliance": "NDA",
      "votes": 0,
      "percentage": 0.0,
      "is_winner": false,
      "is_leading": false
    },
    {
      "name": "Adv. P. V. Sreenijin",
      "party": "CPI(M)",
      "alliance": "LDF",
      "votes": 0,
      "percentage": 0.0,
      "is_winner": false,
      "is_leading": false
    },
    {
      "name": "Manikuttan A. T.",
      "party": "BSP",
      "alliance": "OTH",
      "votes": 0,
      "percentage": 0.0,
      "is_winner": false,
      "is_leading": false
    },
    {
      "name": "Vazhakulam Bhasi",
      "party": "IND",
      "alliance": "OTH",
      "votes": 0,
      "percentage": 0.0,
      "is_winner": false,
      "is_leading": false
    }
  ],
  "results_2021": [
    {
      "candidate": "ADV. P.V.SREENIJIN",
      "party": "CPI(M)",
      "votes": 52351,
      "percentage": 33.79,
      "is_winner": true
    },
    {
      "candidate": "V.P.SAJEENDRAN",
      "party": "INC",
      "votes": 49636,
      "percentage": 32.04,
      "is_winner": false
    },
    {
      "candidate": "RENU SURESH",
      "party": "BJP",
      "votes": 7218,
      "percentage": 4.66,
      "is_winner": false
    },
    {
      "candidate": "KRISHNAN ERANHIKAL",
      "party": "SDPI",
      "votes": 1294,
      "percentage": 0.84,
      "is_winner": false
    },
    {
      "candidate": "SUJITH.K.SURENDRAN",
      "party": "IND",
      "votes": 786,
      "percentage": 0.51,
      "is_winner": false
    }
  ]
}