{
  "constituency": {
    "id": 90,
    "number": 90,
    "name": "THODUPUZHA",
    "district": "Idukki"
  },
  "live_result": {
    "status": "IN_PROGRESS",
    "total_electors": 190161,
    "votes_polled": 134517,
    "votes_counted": 20253,
    "valid_votes": 135021,
    "rounds_completed": 3,
    "total_rounds": 20,
    "last_updated": "2026-05-01T01:58:58.184598+00:00"
  },
  "candidates_2026": [
    {
      "name": "Adv. Basil John",
      "party": "AAP",
      "alliance": "OTH",
      "votes": 8345,
      "percentage": 6.18,
      "is_winner": false,
      "is_leading": true
    },
    {
      "name": "Jomon John",
      "party": "IND",
      "alliance": "OTH",
      "votes": 2121,
      "percentage": 1.57,
      "is_winner": false,
      "is_leading": false
    },
    {
      "name": "Apu John Joseph",
      "party": "KEC",
      "alliance": "UDF",
      "votes": 2086,
      "percentage": 1.54,
      "is_winner": false,
      "is_leading": false
    },
    {
      "name": "P T Varghese",
      "party": "SUCI",
      "alliance": "OTH",
      "votes": 2014,
      "percentage": 1.49,
      "is_winner": false,
      "is_leading": false
    },
    {
      "name": "Afsal M. B",
      "party": "SDPI",
      "alliance": "OTH",
      "votes": 1996,
      "percentage": 1.48,
      "is_winner": false,
      "is_leading": false
    },
    {
      "name": "Adv. Roy A. Varikkad",
      "party": "TTP",
      "alliance": "NDA",
      "votes": 1881,
      "percentage": 1.39,
      "is_winner": false,
      "is_leading": false
    },
    {
      "name": "Cyriac Chazhikadan",
      "party": "KC(M)",
      "alliance": "LDF",
      "votes": 884,
      "percentage": 0.65,
      "is_winner": false,
      "is_leading": false
    },
    {
      "name": "Ajay V Marar (ajay Unni)",
      "party": "IND",
      "alliance": "OTH",
      "votes": 784,
      "percentage": 0.58,
      "is_winner": false,
      "is_leading": false
    }
  ],
  "results_2021": [
    {
      "candidate": "P J JOSEPH",
      "party": "KEC",
      "votes": 67495,
      "percentage": 48.63,
      "is_winner": true
    },
    {
      "candidate": "Prof. K I ANTONY",
      "party": "KC(M)",
      "votes": 47236,
      "percentage": 34.03,
      "is_winner": false
    },
    {
      "candidate": "SHYAMRAJ P",
      "party": "BJP",
      "votes": 21263,
      "percentage": 15.32,
      "is_winner": false
    },
    {
      "candidate": "LEETHESH P T",
      "party": "BSP",
      "votes": 934,
      "percentage": 0.67,
      "is_winner": false
    },
    {
      "candidate": "M T THOMAS",
      "party": "IND",
      "votes": 562,
      "percentage": 0.4,
      "is_winner": false
    }
  ]
}